{
  "metadata": {
    "updated_at": "2026-06-03T01:45:16.295885+00:00",
    "usd_jpy_real": 159.971,
    "usd_jpy_fixed": 150.0
  },
  "summary": {
    "total_asset_fixed": 422050.32714723283,
    "total_asset_real": 429335.53401240887,
    "total_pnl": -77949.67285276717,
    "total_pnl_pct": -15.589934570553432,
    "active_bots": 7,
    "total_bots": 10
  },
  "bots": [
    {
      "name": "01_donchian",
      "display_name": "#01",
      "status": "active",
      "total_jpy_fixed": 40766.784238828695,
      "pnl_jpy": -9233.215761171305,
      "pnl_pct": -18.466431522342607,
      "trade_count_today": 0,
      "positions": [
        {
          "symbol": "BTC/USD",
          "quantity": 0.00038802146221752045,
          "price_usd": 66450.0,
          "value_jpy_fixed": 3867.603924653135
        },
        {
          "symbol": "ETH/USD",
          "quantity": 0.013819361368640821,
          "price_usd": 1849.83,
          "value_jpy_fixed": 3834.5203860829274
        }
      ]
    },
    {
      "name": "02_ema_adx",
      "display_name": "#02",
      "status": "active",
      "total_jpy_fixed": 40366.58308468537,
      "pnl_jpy": -9633.416915314629,
      "pnl_pct": -19.266833830629256,
      "trade_count_today": 2,
      "positions": []
    },
    {
      "name": "03_bb_zscore",
      "display_name": "#03",
      "status": "active",
      "total_jpy_fixed": 45618.72170672345,
      "pnl_jpy": -4381.278293276548,
      "pnl_pct": -8.762556586553096,
      "trade_count_today": 2,
      "positions": []
    },
    {
      "name": "04_vwap",
      "display_name": "#04",
      "status": "active",
      "total_jpy_fixed": 48085.786964210965,
      "pnl_jpy": -1914.2130357890346,
      "pnl_pct": -3.828426071578069,
      "trade_count_today": 0,
      "positions": [
        {
          "symbol": "BTC/USD",
          "quantity": 0.0008907701863508127,
          "price_usd": 66450.0,
          "value_jpy_fixed": 8878.751832451726
        },
        {
          "symbol": "ETH/USD",
          "quantity": 0.0330549623854077,
          "price_usd": 1849.83,
          "value_jpy_fixed": 9171.909160409808
        }
      ]
    },
    {
      "name": "05_squeeze",
      "display_name": "#05",
      "status": "stopped",
      "total_jpy_fixed": 37809.382510949494,
      "pnl_jpy": -12190.617489050506,
      "pnl_pct": -24.381234978101013,
      "trade_count_today": 0,
      "positions": [
        {
          "symbol": "SOL/USD",
          "quantity": 0.9323998058153873,
          "price_usd": 74.19,
          "value_jpy_fixed": 10376.211239016538
        },
        {
          "symbol": "BTC/USD",
          "quantity": 0.0003445061114368947,
          "price_usd": 66450.0,
          "value_jpy_fixed": 3433.864665747248
        }
      ]
    },
    {
      "name": "06_vol_momentum",
      "display_name": "#06",
      "status": "stopped",
      "total_jpy_fixed": 34075.48091307014,
      "pnl_jpy": -15924.51908692986,
      "pnl_pct": -31.84903817385972,
      "trade_count_today": 0,
      "positions": [
        {
          "symbol": "SOL/USD",
          "quantity": 1.5391607594978096,
          "price_usd": 74.19,
          "value_jpy_fixed": 17128.550512071375
        },
        {
          "symbol": "ETH/USD",
          "quantity": 0.0610756318184149,
          "price_usd": 1849.83,
          "value_jpy_fixed": 16946.930400998765
        }
      ]
    },
    {
      "name": "07_pair_trade",
      "display_name": "#07",
      "status": "active",
      "total_jpy_fixed": 42757.09614434405,
      "pnl_jpy": -7242.9038556559535,
      "pnl_pct": -14.485807711311907,
      "trade_count_today": 0,
      "positions": []
    },
    {
      "name": "08_regime",
      "display_name": "#08",
      "status": "stopped",
      "total_jpy_fixed": 39150.170462564514,
      "pnl_jpy": -10849.829537435486,
      "pnl_pct": -21.699659074870972,
      "trade_count_today": 0,
      "positions": [
        {
          "symbol": "BTC/USD",
          "quantity": 0.0011177759698988267,
          "price_usd": 66450.0,
          "value_jpy_fixed": 11141.431979966555
        }
      ]
    },
    {
      "name": "09_ml_gate",
      "display_name": "#09",
      "status": "active",
      "total_jpy_fixed": 47431.478305918645,
      "pnl_jpy": -2568.5216940813552,
      "pnl_pct": -5.13704338816271,
      "trade_count_today": 0,
      "positions": [
        {
          "symbol": "BTC/USD",
          "quantity": 0.00040318315171493396,
          "price_usd": 66450.0,
          "value_jpy_fixed": 4018.728064718604
        },
        {
          "symbol": "ETH/USD",
          "quantity": 0.0159971599924028,
          "price_usd": 1849.83,
          "value_jpy_fixed": 4438.80397031197
        }
      ]
    },
    {
      "name": "10_deriv",
      "display_name": "#10",
      "status": "active",
      "total_jpy_fixed": 45988.842815937525,
      "pnl_jpy": -4011.1571840624747,
      "pnl_pct": -8.022314368124949,
      "trade_count_today": 0,
      "positions": [
        {
          "symbol": "BTC/USD",
          "quantity": 0.0008495823539220568,
          "price_usd": 66450.0,
          "value_jpy_fixed": 8468.212112718102
        },
        {
          "symbol": "ETH/USD",
          "quantity": 0.028436533551408308,
          "price_usd": 1849.83,
          "value_jpy_fixed": 7890.412928910244
        }
      ]
    }
  ],
  "recent_trades": [
    {
      "timestamp": "2026-06-03T00:13:54.061175+00:00",
      "bot": "03",
      "action": "SELL",
      "symbol": "ETH/USD",
      "price": 279670.5,
      "quantity": 0.0321663934620232,
      "icon": "🔴"
    },
    {
      "timestamp": "2026-06-03T00:13:54.058051+00:00",
      "bot": "03",
      "action": "SELL",
      "symbol": "BTC/USD",
      "price": 10007640.0,
      "quantity": 0.0009069660420277897,
      "icon": "🔴"
    },
    {
      "timestamp": "2026-06-03T00:13:54.044415+00:00",
      "bot": "02",
      "action": "SELL",
      "symbol": "ETH/USD",
      "price": 279670.5,
      "quantity": 0.013740515307870328,
      "icon": "🔴"
    },
    {
      "timestamp": "2026-06-03T00:13:54.041407+00:00",
      "bot": "02",
      "action": "SELL",
      "symbol": "BTC/USD",
      "price": 10007640.0,
      "quantity": 0.0004002054689064074,
      "icon": "🔴"
    },
    {
      "timestamp": "2026-06-02T20:24:18.451440+00:00",
      "bot": "03",
      "action": "BUY",
      "symbol": "ETH/USD",
      "price": 284580.0,
      "quantity": 0.0321663934620232,
      "icon": "🟢"
    },
    {
      "timestamp": "2026-06-02T17:19:48.939497+00:00",
      "bot": "07",
      "action": "SELL",
      "symbol": "BTC/USD",
      "price": 10115940.0,
      "quantity": 0.0029397487184972667,
      "icon": "🔴"
    },
    {
      "timestamp": "2026-06-02T17:19:48.914876+00:00",
      "bot": "03",
      "action": "SELL",
      "symbol": "ETH/USD",
      "price": 288222.0,
      "quantity": 0.031023360934276448,
      "icon": "🔴"
    },
    {
      "timestamp": "2026-06-02T17:19:48.912007+00:00",
      "bot": "03",
      "action": "BUY",
      "symbol": "BTC/USD",
      "price": 10115940.0,
      "quantity": 0.0009069660420277897,
      "icon": "🟢"
    },
    {
      "timestamp": "2026-06-02T17:19:48.898565+00:00",
      "bot": "02",
      "action": "BUY",
      "symbol": "BTC/USD",
      "price": 10115940.0,
      "quantity": 0.0004002054689064074,
      "icon": "🟢"
    },
    {
      "timestamp": "2026-06-02T12:51:11.746933+00:00",
      "bot": "07",
      "action": "BUY",
      "symbol": "BTC/USD",
      "price": 10353120.0,
      "quantity": 0.0029397487184972667,
      "icon": "🟢"
    },
    {
      "timestamp": "2026-06-02T09:07:18.188078+00:00",
      "bot": "03",
      "action": "SELL",
      "symbol": "BTC/USD",
      "price": 10426470.0,
      "quantity": 0.0008703032981412012,
      "icon": "🔴"
    },
    {
      "timestamp": "2026-06-02T09:07:18.174698+00:00",
      "bot": "02",
      "action": "SELL",
      "symbol": "ETH/USD",
      "price": 295938.0,
      "quantity": 0.027286000743403864,
      "icon": "🔴"
    },
    {
      "timestamp": "2026-06-02T09:07:18.171415+00:00",
      "bot": "02",
      "action": "SELL",
      "symbol": "BTC/USD",
      "price": 10426470.0,
      "quantity": 0.0003854970851474405,
      "icon": "🔴"
    },
    {
      "timestamp": "2026-06-02T05:00:12.593810+00:00",
      "bot": "03",
      "action": "BUY",
      "symbol": "ETH/USD",
      "price": 299080.5,
      "quantity": 0.031023360934276448,
      "icon": "🟢"
    },
    {
      "timestamp": "2026-06-02T05:00:12.577991+00:00",
      "bot": "02",
      "action": "SELL",
      "symbol": "BTC/USD",
      "price": 10604250.0,
      "quantity": 0.0007657244823831342,
      "icon": "🔴"
    },
    {
      "timestamp": "2026-06-02T05:00:12.565146+00:00",
      "bot": "01",
      "action": "SELL",
      "symbol": "ETH/USD",
      "price": 299080.5,
      "quantity": 0.04140925606151645,
      "icon": "🔴"
    }
  ]
}