{
  "metadata": {
    "updated_at": "2026-05-12T00:08:40.859209+00:00",
    "usd_jpy_real": 159.361,
    "usd_jpy_fixed": 150.0
  },
  "summary": {
    "total_asset_fixed": 484866.43407946033,
    "total_asset_real": 494908.48394183954,
    "total_pnl": -15133.565920539666,
    "total_pnl_pct": -3.026713184107933,
    "active_bots": 10,
    "total_bots": 10
  },
  "bots": [
    {
      "name": "01_donchian",
      "display_name": "#01",
      "status": "active",
      "total_jpy_fixed": 48854.68982722525,
      "pnl_jpy": -1145.310172774749,
      "pnl_pct": -2.290620345549498,
      "trade_count_today": 0,
      "positions": [
        {
          "symbol": "ETH/USD",
          "quantity": 0.05582059421326206,
          "price_usd": 2337.25,
          "value_jpy_fixed": 19570.002573742015
        },
        {
          "symbol": "BTC/USD",
          "quantity": 0.00039888188315174034,
          "price_usd": 81657.0,
          "value_jpy_fixed": 4885.724689878249
        }
      ]
    },
    {
      "name": "02_ema_adx",
      "display_name": "#02",
      "status": "active",
      "total_jpy_fixed": 48428.10476991432,
      "pnl_jpy": -1571.8952300856836,
      "pnl_pct": -3.1437904601713673,
      "trade_count_today": 0,
      "positions": [
        {
          "symbol": "BTC/USD",
          "quantity": 0.00039566165667988045,
          "price_usd": 81657.0,
          "value_jpy_fixed": 4846.28158492635
        },
        {
          "symbol": "ETH/USD",
          "quantity": 0.041405627903812615,
          "price_usd": 2337.25,
          "value_jpy_fixed": 14516.295572727904
        }
      ]
    },
    {
      "name": "03_bb_zscore",
      "display_name": "#03",
      "status": "active",
      "total_jpy_fixed": 50283.9244662372,
      "pnl_jpy": 283.92446623720025,
      "pnl_pct": 0.5678489324744005,
      "trade_count_today": 0,
      "positions": [
        {
          "symbol": "BTC/USD",
          "quantity": 0.000819516152194896,
          "price_usd": 81657.0,
          "value_jpy_fixed": 10037.884565966793
        }
      ]
    },
    {
      "name": "04_vwap",
      "display_name": "#04",
      "status": "active",
      "total_jpy_fixed": 53176.46716357057,
      "pnl_jpy": 3176.467163570567,
      "pnl_pct": 6.352934327141134,
      "trade_count_today": 0,
      "positions": [
        {
          "symbol": "BTC/USD",
          "quantity": 0.0008672599742502968,
          "price_usd": 81657.0,
          "value_jpy_fixed": 10622.677157603473
        },
        {
          "symbol": "ETH/USD",
          "quantity": 0.03001356729109854,
          "price_usd": 2337.25,
          "value_jpy_fixed": 10522.381522668009
        }
      ]
    },
    {
      "name": "05_squeeze",
      "display_name": "#05",
      "status": "active",
      "total_jpy_fixed": 47648.103493024566,
      "pnl_jpy": -2351.896506975434,
      "pnl_pct": -4.703793013950868,
      "trade_count_today": 0,
      "positions": [
        {
          "symbol": "ETH/USD",
          "quantity": 0.04074183542103446,
          "price_usd": 2337.25,
          "value_jpy_fixed": 14283.57822567192
        },
        {
          "symbol": "BTC/USD",
          "quantity": 0.0003890025057098586,
          "price_usd": 81657.0,
          "value_jpy_fixed": 4764.716641312489
        }
      ]
    },
    {
      "name": "06_vol_momentum",
      "display_name": "#06",
      "status": "active",
      "total_jpy_fixed": 42788.46635588122,
      "pnl_jpy": -7211.533644118783,
      "pnl_pct": -14.423067288237565,
      "trade_count_today": 0,
      "positions": [
        {
          "symbol": "BTC/USD",
          "quantity": 0.000698299405935081,
          "price_usd": 81657.0,
          "value_jpy_fixed": 8553.155188566137
        }
      ]
    },
    {
      "name": "07_pair_trade",
      "display_name": "#07",
      "status": "active",
      "total_jpy_fixed": 47313.420925694096,
      "pnl_jpy": -2686.579074305904,
      "pnl_pct": -5.373158148611808,
      "trade_count_today": 0,
      "positions": []
    },
    {
      "name": "08_regime",
      "display_name": "#08",
      "status": "active",
      "total_jpy_fixed": 46586.77267538848,
      "pnl_jpy": -3413.227324611522,
      "pnl_pct": -6.826454649223043,
      "trade_count_today": 0,
      "positions": [
        {
          "symbol": "ETH/USD",
          "quantity": 0.0400569724640368,
          "price_usd": 2337.25,
          "value_jpy_fixed": 14043.4738337355
        },
        {
          "symbol": "BTC/USD",
          "quantity": 0.0011413534782185476,
          "price_usd": 81657.0,
          "value_jpy_fixed": 13979.92514563379
        }
      ]
    },
    {
      "name": "09_ml_gate",
      "display_name": "#09",
      "status": "active",
      "total_jpy_fixed": 49780.62148062905,
      "pnl_jpy": -219.3785193709482,
      "pnl_pct": -0.43875703874189637,
      "trade_count_today": 0,
      "positions": [
        {
          "symbol": "BTC/USD",
          "quantity": 0.00040318315171493396,
          "price_usd": 81657.0,
          "value_jpy_fixed": 4938.408992937954
        },
        {
          "symbol": "ETH/USD",
          "quantity": 0.014184601114346093,
          "price_usd": 2337.25,
          "value_jpy_fixed": 4972.943843175811
        }
      ]
    },
    {
      "name": "10_deriv",
      "display_name": "#10",
      "status": "active",
      "total_jpy_fixed": 50005.862921895554,
      "pnl_jpy": 5.862921895553882,
      "pnl_pct": 0.011725843791107764,
      "trade_count_today": 0,
      "positions": [
        {
          "symbol": "BTC/USD",
          "quantity": 0.0008495823539220568,
          "price_usd": 81657.0,
          "value_jpy_fixed": 10406.15194113201
        },
        {
          "symbol": "ETH/USD",
          "quantity": 0.028436533551408308,
          "price_usd": 2337.25,
          "value_jpy_fixed": 9969.493206454361
        }
      ]
    }
  ],
  "recent_trades": [
    {
      "timestamp": "2026-05-11T23:40:30.332205+00:00",
      "bot": "06",
      "action": "SELL",
      "symbol": "BTC/USD",
      "price": 12258990.0,
      "quantity": 0.00035188163360459654,
      "icon": "🔴"
    },
    {
      "timestamp": "2026-05-11T23:40:30.322838+00:00",
      "bot": "05",
      "action": "SELL",
      "symbol": "SOL/USD",
      "price": 14610.0,
      "quantity": 0.3261688315195477,
      "icon": "🔴"
    },
    {
      "timestamp": "2026-05-11T23:40:30.319807+00:00",
      "bot": "05",
      "action": "SELL",
      "symbol": "BTC/USD",
      "price": 12258990.0,
      "quantity": 0.0007769779221907585,
      "icon": "🔴"
    },
    {
      "timestamp": "2026-05-11T23:40:30.304394+00:00",
      "bot": "03",
      "action": "BUY",
      "symbol": "BTC/USD",
      "price": 12258990.0,
      "quantity": 0.000819516152194896,
      "icon": "🟢"
    },
    {
      "timestamp": "2026-05-11T22:39:24.002862+00:00",
      "bot": "07",
      "action": "SELL",
      "symbol": "BTC/USD",
      "price": 12264645.0,
      "quantity": 0.002702428273940806,
      "icon": "🔴"
    },
    {
      "timestamp": "2026-05-11T22:39:23.997746+00:00",
      "bot": "06",
      "action": "SELL",
      "symbol": "SOL/USD",
      "price": 14628.0,
      "quantity": 1.462121213125887,
      "icon": "🔴"
    },
    {
      "timestamp": "2026-05-11T22:39:23.994483+00:00",
      "bot": "06",
      "action": "SELL",
      "symbol": "ETH/USD",
      "price": 351016.5,
      "quantity": 0.02445787803731745,
      "icon": "🔴"
    },
    {
      "timestamp": "2026-05-11T22:39:23.991539+00:00",
      "bot": "06",
      "action": "BUY",
      "symbol": "BTC/USD",
      "price": 12264645.0,
      "quantity": 0.0010488695549034047,
      "icon": "🟢"
    },
    {
      "timestamp": "2026-05-11T22:39:23.982928+00:00",
      "bot": "05",
      "action": "BUY",
      "symbol": "ETH/USD",
      "price": 351016.5,
      "quantity": 0.027149540279026416,
      "icon": "🟢"
    },
    {
      "timestamp": "2026-05-11T22:39:23.979601+00:00",
      "bot": "05",
      "action": "BUY",
      "symbol": "BTC/USD",
      "price": 12264645.0,
      "quantity": 0.0011659804279006171,
      "icon": "🟢"
    },
    {
      "timestamp": "2026-05-11T22:39:23.963801+00:00",
      "bot": "03",
      "action": "SELL",
      "symbol": "BTC/USD",
      "price": 12264645.0,
      "quantity": 0.0008189661175329134,
      "icon": "🔴"
    },
    {
      "timestamp": "2026-05-11T21:42:10.151239+00:00",
      "bot": "08",
      "action": "SELL",
      "symbol": "BTC/USD",
      "price": 12258435.0,
      "quantity": 0.0015166096314007077,
      "icon": "🔴"
    },
    {
      "timestamp": "2026-05-11T21:42:10.100595+00:00",
      "bot": "07",
      "action": "BUY",
      "symbol": "BTC/USD",
      "price": 12258435.0,
      "quantity": 0.002702428273940806,
      "icon": "🟢"
    },
    {
      "timestamp": "2026-05-11T21:42:10.092575+00:00",
      "bot": "06",
      "action": "SELL",
      "symbol": "ETH/USD",
      "price": 350872.5,
      "quantity": 0.036773080692971756,
      "icon": "🔴"
    },
    {
      "timestamp": "2026-05-11T21:42:10.088761+00:00",
      "bot": "06",
      "action": "BUY",
      "symbol": "BTC/USD",
      "price": 12258435.0,
      "quantity": 1.3114846362729867e-06,
      "icon": "🟢"
    },
    {
      "timestamp": "2026-05-11T21:42:10.077515+00:00",
      "bot": "05",
      "action": "SELL",
      "symbol": "SOL/USD",
      "price": 14641.5,
      "quantity": 0.6499811078796903,
      "icon": "🔴"
    },
    {
      "timestamp": "2026-05-11T21:42:10.073708+00:00",
      "bot": "05",
      "action": "BUY",
      "symbol": "ETH/USD",
      "price": 350872.5,
      "quantity": 0.013592295142008042,
      "icon": "🟢"
    },
    {
      "timestamp": "2026-05-11T21:42:10.055939+00:00",
      "bot": "03",
      "action": "SELL",
      "symbol": "ETH/USD",
      "price": 350872.5,
      "quantity": 0.028685036324921673,
      "icon": "🔴"
    },
    {
      "timestamp": "2026-05-11T21:42:10.039471+00:00",
      "bot": "02",
      "action": "BUY",
      "symbol": "ETH/USD",
      "price": 350872.5,
      "quantity": 0.013703987908957748,
      "icon": "🟢"
    },
    {
      "timestamp": "2026-05-11T21:42:10.035294+00:00",
      "bot": "02",
      "action": "SELL",
      "symbol": "BTC/USD",
      "price": 12258435.0,
      "quantity": 0.002768052416522094,
      "icon": "🔴"
    },
    {
      "timestamp": "2026-05-11T21:42:10.021261+00:00",
      "bot": "01",
      "action": "SELL",
      "symbol": "BTC/USD",
      "price": 12258435.0,
      "quantity": 0.0012037822087959343,
      "icon": "🔴"
    },
    {
      "timestamp": "2026-05-11T20:15:32.164647+00:00",
      "bot": "06",
      "action": "BUY",
      "symbol": "SOL/USD",
      "price": 14680.5,
      "quantity": 0.8741505021736938,
      "icon": "🟢"
    },
    {
      "timestamp": "2026-05-11T20:15:32.162213+00:00",
      "bot": "06",
      "action": "BUY",
      "symbol": "ETH/USD",
      "price": 350604.0,
      "quantity": 0.061230958730289206,
      "icon": "🟢"
    },
    {
      "timestamp": "2026-05-11T20:15:32.159695+00:00",
      "bot": "06",
      "action": "SELL",
      "symbol": "BTC/USD",
      "price": 12283905.0,
      "quantity": 0.0006993181767021025,
      "icon": "🔴"
    },
    {
      "timestamp": "2026-05-11T20:15:32.151401+00:00",
      "bot": "05",
      "action": "BUY",
      "symbol": "SOL/USD",
      "price": 14680.5,
      "quantity": 0.6487862701297221,
      "icon": "🟢"
    },
    {
      "timestamp": "2026-05-11T20:15:32.148727+00:00",
      "bot": "05",
      "action": "SELL",
      "symbol": "ETH/USD",
      "price": 350604.0,
      "quantity": 0.04090847519564009,
      "icon": "🔴"
    },
    {
      "timestamp": "2026-05-11T20:15:32.146022+00:00",
      "bot": "05",
      "action": "SELL",
      "symbol": "BTC/USD",
      "price": 12283905.0,
      "quantity": 0.0011696097261910331,
      "icon": "🔴"
    },
    {
      "timestamp": "2026-05-11T20:15:32.131414+00:00",
      "bot": "03",
      "action": "BUY",
      "symbol": "ETH/USD",
      "price": 350604.0,
      "quantity": 0.028685036324921673,
      "icon": "🟢"
    },
    {
      "timestamp": "2026-05-11T20:15:32.128598+00:00",
      "bot": "03",
      "action": "BUY",
      "symbol": "BTC/USD",
      "price": 12283905.0,
      "quantity": 0.0008189661175329134,
      "icon": "🟢"
    },
    {
      "timestamp": "2026-05-11T18:27:24.705281+00:00",
      "bot": "08",
      "action": "BUY",
      "symbol": "BTC/USD",
      "price": 12286185.0,
      "quantity": 0.0026579631096192552,
      "icon": "🟢"
    },
    {
      "timestamp": "2026-05-11T18:27:24.668864+00:00",
      "bot": "07",
      "action": "SELL",
      "symbol": "ETH/USD",
      "price": 350749.5,
      "quantity": 0.09475669793723006,
      "icon": "🔴"
    },
    {
      "timestamp": "2026-05-11T18:27:24.663123+00:00",
      "bot": "06",
      "action": "SELL",
      "symbol": "ETH/USD",
      "price": 350749.5,
      "quantity": 0.0609568418697027,
      "icon": "🔴"
    },
    {
      "timestamp": "2026-05-11T18:27:24.660513+00:00",
      "bot": "06",
      "action": "BUY",
      "symbol": "BTC/USD",
      "price": 12286185.0,
      "quantity": 0.0006993181767021025,
      "icon": "🟢"
    },
    {
      "timestamp": "2026-05-11T18:27:24.651919+00:00",
      "bot": "05",
      "action": "SELL",
      "symbol": "SOL/USD",
      "price": 14620.5,
      "quantity": 0.6677062568536246,
      "icon": "🔴"
    },
    {
      "timestamp": "2026-05-11T18:27:24.648904+00:00",
      "bot": "05",
      "action": "BUY",
      "symbol": "ETH/USD",
      "price": 350749.5,
      "quantity": 0.02724603288428906,
      "icon": "🟢"
    },
    {
      "timestamp": "2026-05-11T18:27:24.634924+00:00",
      "bot": "03",
      "action": "SELL",
      "symbol": "ETH/USD",
      "price": 350749.5,
      "quantity": 0.028811360208581587,
      "icon": "🔴"
    },
    {
      "timestamp": "2026-05-11T16:46:54.971401+00:00",
      "bot": "08",
      "action": "BUY",
      "symbol": "ETH/USD",
      "price": 349390.5,
      "quantity": 0.0400569724640368,
      "icon": "🟢"
    },
    {
      "timestamp": "2026-05-11T16:46:54.922425+00:00",
      "bot": "07",
      "action": "BUY",
      "symbol": "ETH/USD",
      "price": 349390.5,
      "quantity": 0.09475669793723006,
      "icon": "🟢"
    },
    {
      "timestamp": "2026-05-11T16:46:54.916003+00:00",
      "bot": "06",
      "action": "SELL",
      "symbol": "SOL/USD",
      "price": 14611.5,
      "quantity": 0.8942815394063246,
      "icon": "🔴"
    },
    {
      "timestamp": "2026-05-11T16:46:54.912804+00:00",
      "bot": "06",
      "action": "BUY",
      "symbol": "ETH/USD",
      "price": 349390.5,
      "quantity": 0.0609568418697027,
      "icon": "🟢"
    },
    {
      "timestamp": "2026-05-11T16:46:54.901715+00:00",
      "bot": "05",
      "action": "BUY",
      "symbol": "ETH/USD",
      "price": 349390.5,
      "quantity": 0.013662442311351027,
      "icon": "🟢"
    },
    {
      "timestamp": "2026-05-11T16:46:54.872881+00:00",
      "bot": "02",
      "action": "BUY",
      "symbol": "ETH/USD",
      "price": 349390.5,
      "quantity": 0.027701639994854865,
      "icon": "🟢"
    },
    {
      "timestamp": "2026-05-11T16:46:54.868864+00:00",
      "bot": "02",
      "action": "BUY",
      "symbol": "BTC/USD",
      "price": 12244035.0,
      "quantity": 0.001971337678773204,
      "icon": "🟢"
    },
    {
      "timestamp": "2026-05-11T16:46:54.855678+00:00",
      "bot": "01",
      "action": "BUY",
      "symbol": "ETH/USD",
      "price": 349390.5,
      "quantity": 0.04186157603923339,
      "icon": "🟢"
    },
    {
      "timestamp": "2026-05-11T14:08:27.573221+00:00",
      "bot": "08",
      "action": "SELL",
      "symbol": "ETH/USD",
      "price": 349039.5,
      "quantity": 0.040053312747659234,
      "icon": "🔴"
    },
    {
      "timestamp": "2026-05-11T14:08:27.568713+00:00",
      "bot": "08",
      "action": "SELL",
      "symbol": "BTC/USD",
      "price": 12177105.0,
      "quantity": 0.0011572023813634581,
      "icon": "🔴"
    },
    {
      "timestamp": "2026-05-11T14:08:27.512750+00:00",
      "bot": "06",
      "action": "BUY",
      "symbol": "SOL/USD",
      "price": 14368.500000000002,
      "quantity": 1.4822522503585176,
      "icon": "🟢"
    },
    {
      "timestamp": "2026-05-11T14:08:27.509144+00:00",
      "bot": "06",
      "action": "SELL",
      "symbol": "ETH/USD",
      "price": 349039.5,
      "quantity": 0.06100944199375703,
      "icon": "🔴"
    },
    {
      "timestamp": "2026-05-11T14:08:27.498543+00:00",
      "bot": "05",
      "action": "SELL",
      "symbol": "ETH/USD",
      "price": 349039.5,
      "quantity": 0.04067307186593334,
      "icon": "🔴"
    },
    {
      "timestamp": "2026-05-11T14:08:27.495044+00:00",
      "bot": "05",
      "action": "BUY",
      "symbol": "BTC/USD",
      "price": 12177105.0,
      "quantity": 0.0007794735536872137,
      "icon": "🟢"
    }
  ]
}