{
  "metadata": {
    "updated_at": "2026-06-27T10:20:08.700452+00:00",
    "usd_jpy_real": 158.704,
    "usd_jpy_fixed": 150.0
  },
  "summary": {
    "total_asset_fixed": 406143.6783394428,
    "total_asset_real": 413136.21620862087,
    "total_pnl": -93856.32166055718,
    "total_pnl_pct": -18.771264332111436,
    "active_bots": 5,
    "total_bots": 10
  },
  "bots": [
    {
      "name": "01_donchian",
      "display_name": "#01",
      "status": "stopped",
      "total_jpy_fixed": 38021.21138557306,
      "pnl_jpy": -11978.788614426943,
      "pnl_pct": -23.957577228853886,
      "trade_count_today": 0,
      "positions": [
        {
          "symbol": "ETH/USD",
          "quantity": 0.0600260064610979,
          "price_usd": 1581.59,
          "value_jpy_fixed": 14240.479733821174
        },
        {
          "symbol": "BTC/USD",
          "quantity": 0.0004193929525974449,
          "price_usd": 60369.0,
          "value_jpy_fixed": 3797.749973303273
        }
      ]
    },
    {
      "name": "02_ema_adx",
      "display_name": "#02",
      "status": "stopped",
      "total_jpy_fixed": 39427.048307320176,
      "pnl_jpy": -10572.951692679824,
      "pnl_pct": -21.14590338535965,
      "trade_count_today": 0,
      "positions": [
        {
          "symbol": "ETH/USD",
          "quantity": 0.014442908385121273,
          "price_usd": 1581.59,
          "value_jpy_fixed": 3426.413920923593
        }
      ]
    },
    {
      "name": "03_bb_zscore",
      "display_name": "#03",
      "status": "active",
      "total_jpy_fixed": 40712.84164892218,
      "pnl_jpy": -9287.158351077822,
      "pnl_pct": -18.574316702155645,
      "trade_count_today": 4,
      "positions": []
    },
    {
      "name": "04_vwap",
      "display_name": "#04",
      "status": "active",
      "total_jpy_fixed": 46586.76634378641,
      "pnl_jpy": -3413.2336562135897,
      "pnl_pct": -6.82646731242718,
      "trade_count_today": 0,
      "positions": [
        {
          "symbol": "BTC/USD",
          "quantity": 0.001024897577108115,
          "price_usd": 60369.0,
          "value_jpy_fixed": 9280.80627486597
        },
        {
          "symbol": "ETH/USD",
          "quantity": 0.03974601722997401,
          "price_usd": 1581.59,
          "value_jpy_fixed": 9429.285508613188
        }
      ]
    },
    {
      "name": "05_squeeze",
      "display_name": "#05",
      "status": "stopped",
      "total_jpy_fixed": 37163.67313043496,
      "pnl_jpy": -12836.32686956504,
      "pnl_pct": -25.67265373913008,
      "trade_count_today": 0,
      "positions": [
        {
          "symbol": "SOL/USD",
          "quantity": 0.9323998058153873,
          "price_usd": 71.82,
          "value_jpy_fixed": 10044.743108049166
        },
        {
          "symbol": "BTC/USD",
          "quantity": 0.0003445061114368947,
          "price_usd": 60369.0,
          "value_jpy_fixed": 3119.6234162000846
        }
      ]
    },
    {
      "name": "06_vol_momentum",
      "display_name": "#06",
      "status": "stopped",
      "total_jpy_fixed": 31070.870141222924,
      "pnl_jpy": -18929.129858777076,
      "pnl_pct": -37.858259717554155,
      "trade_count_today": 0,
      "positions": [
        {
          "symbol": "SOL/USD",
          "quantity": 1.5391607594978096,
          "price_usd": 71.82,
          "value_jpy_fixed": 16581.3788620699
        },
        {
          "symbol": "ETH/USD",
          "quantity": 0.0610756318184149,
          "price_usd": 1581.59,
          "value_jpy_fixed": 14489.491279153022
        }
      ]
    },
    {
      "name": "07_pair_trade",
      "display_name": "#07",
      "status": "active",
      "total_jpy_fixed": 43968.30118184407,
      "pnl_jpy": -6031.698818155928,
      "pnl_pct": -12.063397636311857,
      "trade_count_today": 0,
      "positions": []
    },
    {
      "name": "08_regime",
      "display_name": "#08",
      "status": "stopped",
      "total_jpy_fixed": 38130.5911116213,
      "pnl_jpy": -11869.408888378697,
      "pnl_pct": -23.738817776757397,
      "trade_count_today": 0,
      "positions": [
        {
          "symbol": "BTC/USD",
          "quantity": 0.0011177759698988267,
          "price_usd": 60369.0,
          "value_jpy_fixed": 10121.852629023342
        }
      ]
    },
    {
      "name": "09_ml_gate",
      "display_name": "#09",
      "status": "active",
      "total_jpy_fixed": 46901.90976458119,
      "pnl_jpy": -3098.0902354188074,
      "pnl_pct": -6.196180470837615,
      "trade_count_today": 0,
      "positions": [
        {
          "symbol": "BTC/USD",
          "quantity": 0.0004929277937355478,
          "price_usd": 60369.0,
          "value_jpy_fixed": 4463.6336970031925
        },
        {
          "symbol": "ETH/USD",
          "quantity": 0.01987742179016123,
          "price_usd": 1581.59,
          "value_jpy_fixed": 4715.689729365165
        }
      ]
    },
    {
      "name": "10_deriv",
      "display_name": "#10",
      "status": "active",
      "total_jpy_fixed": 44160.465324136545,
      "pnl_jpy": -5839.534675863455,
      "pnl_pct": -11.67906935172691,
      "trade_count_today": 0,
      "positions": [
        {
          "symbol": "BTC/USD",
          "quantity": 0.0008495823539220568,
          "price_usd": 60369.0,
          "value_jpy_fixed": 7693.265568588096
        },
        {
          "symbol": "ETH/USD",
          "quantity": 0.03836299408899608,
          "price_usd": 1581.59,
          "value_jpy_fixed": 9101.179173182296
        }
      ]
    }
  ],
  "recent_trades": [
    {
      "timestamp": "2026-06-27T08:16:38.840033+00:00",
      "bot": "03",
      "action": "SELL",
      "symbol": "ETH/USD",
      "price": 237312.0,
      "quantity": 0.03438052674721795,
      "icon": "🔴"
    },
    {
      "timestamp": "2026-06-27T08:16:38.836822+00:00",
      "bot": "03",
      "action": "SELL",
      "symbol": "BTC/USD",
      "price": 9060660.0,
      "quantity": 0.0009038635079223103,
      "icon": "🔴"
    },
    {
      "timestamp": "2026-06-27T01:34:11.014766+00:00",
      "bot": "03",
      "action": "BUY",
      "symbol": "ETH/USD",
      "price": 236011.5,
      "quantity": 0.03438052674721795,
      "icon": "🟢"
    },
    {
      "timestamp": "2026-06-27T01:34:11.010772+00:00",
      "bot": "03",
      "action": "BUY",
      "symbol": "BTC/USD",
      "price": 8979930.0,
      "quantity": 0.0009038635079223103,
      "icon": "🟢"
    },
    {
      "timestamp": "2026-06-26T22:09:32.321140+00:00",
      "bot": "03",
      "action": "SELL",
      "symbol": "ETH/USD",
      "price": 235642.5,
      "quantity": 0.03448515277217398,
      "icon": "🔴"
    },
    {
      "timestamp": "2026-06-26T22:09:32.317289+00:00",
      "bot": "03",
      "action": "SELL",
      "symbol": "BTC/USD",
      "price": 8967675.0,
      "quantity": 0.000908153942155843,
      "icon": "🔴"
    },
    {
      "timestamp": "2026-06-26T19:03:11.204482+00:00",
      "bot": "03",
      "action": "BUY",
      "symbol": "ETH/USD",
      "price": 235386.0,
      "quantity": 0.03448515277217398,
      "icon": "🟢"
    },
    {
      "timestamp": "2026-06-26T19:03:11.201453+00:00",
      "bot": "03",
      "action": "BUY",
      "symbol": "BTC/USD",
      "price": 8940945.0,
      "quantity": 0.000908153942155843,
      "icon": "🟢"
    },
    {
      "timestamp": "2026-06-26T10:28:39.003528+00:00",
      "bot": "07",
      "action": "SELL",
      "symbol": "BTC/USD",
      "price": 8954190.0,
      "quantity": 0.0014345730106809704,
      "icon": "🔴"
    },
    {
      "timestamp": "2026-06-26T10:28:38.981022+00:00",
      "bot": "04",
      "action": "BUY",
      "symbol": "ETH/USD",
      "price": 232890.0,
      "quantity": 0.02003977952279207,
      "icon": "🟢"
    }
  ]
}