{
  "metadata": {
    "updated_at": "2026-07-23T16:42:02.051513+00:00",
    "usd_jpy_real": 162.044,
    "usd_jpy_fixed": 150.0
  },
  "summary": {
    "total_asset_fixed": 418637.0713281899,
    "total_asset_real": 431664.4289425842,
    "total_pnl": -81362.92867181008,
    "total_pnl_pct": -16.272585734362018,
    "active_bots": 5,
    "total_bots": 10
  },
  "bots": [
    {
      "name": "01_donchian",
      "display_name": "#01",
      "status": "stopped",
      "total_jpy_fixed": 41040.50503495753,
      "pnl_jpy": -8959.494965042468,
      "pnl_pct": -17.918989930084937,
      "trade_count_today": 0,
      "positions": [
        {
          "symbol": "ETH/USD",
          "quantity": 0.0600260064610979,
          "price_usd": 1886.8,
          "value_jpy_fixed": 16988.56034861993
        },
        {
          "symbol": "BTC/USD",
          "quantity": 0.0004193929525974449,
          "price_usd": 64680.2,
          "value_jpy_fixed": 4068.9630078889886
        }
      ]
    },
    {
      "name": "02_ema_adx",
      "display_name": "#02",
      "status": "stopped",
      "total_jpy_fixed": 40088.26631755361,
      "pnl_jpy": -9911.733682446393,
      "pnl_pct": -19.823467364892785,
      "trade_count_today": 0,
      "positions": [
        {
          "symbol": "ETH/USD",
          "quantity": 0.014442908385121273,
          "price_usd": 1886.8,
          "value_jpy_fixed": 4087.631931157023
        }
      ]
    },
    {
      "name": "03_bb_zscore",
      "display_name": "#03",
      "status": "active",
      "total_jpy_fixed": 41636.65723030528,
      "pnl_jpy": -8363.342769694718,
      "pnl_pct": -16.726685539389436,
      "trade_count_today": 1,
      "positions": [
        {
          "symbol": "ETH/USD",
          "quantity": 0.02937377693331027,
          "price_usd": 1886.8,
          "value_jpy_fixed": 8313.366347665473
        }
      ]
    },
    {
      "name": "04_vwap",
      "display_name": "#04",
      "status": "active",
      "total_jpy_fixed": 46594.177558088806,
      "pnl_jpy": -3405.822441911194,
      "pnl_pct": -6.811644883822387,
      "trade_count_today": 2,
      "positions": [
        {
          "symbol": "BTC/USD",
          "quantity": 0.002403980005939694,
          "price_usd": 64680.2,
          "value_jpy_fixed": 23323.48613702709
        },
        {
          "symbol": "ETH/USD",
          "quantity": 0.0821728431145306,
          "price_usd": 1886.8,
          "value_jpy_fixed": 23256.558058274448
        }
      ]
    },
    {
      "name": "05_squeeze",
      "display_name": "#05",
      "status": "stopped",
      "total_jpy_fixed": 37969.67442111649,
      "pnl_jpy": -12030.325578883509,
      "pnl_pct": -24.06065115776702,
      "trade_count_today": 0,
      "positions": [
        {
          "symbol": "SOL/USD",
          "quantity": 0.9323998058153873,
          "price_usd": 75.99,
          "value_jpy_fixed": 10627.95918658669
        },
        {
          "symbol": "BTC/USD",
          "quantity": 0.0003445061114368947,
          "price_usd": 64680.2,
          "value_jpy_fixed": 3342.408628344095
        }
      ]
    },
    {
      "name": "06_vol_momentum",
      "display_name": "#06",
      "status": "stopped",
      "total_jpy_fixed": 34829.74923438356,
      "pnl_jpy": -15170.250765616438,
      "pnl_pct": -30.340501531232878,
      "trade_count_today": 0,
      "positions": [
        {
          "symbol": "SOL/USD",
          "quantity": 1.5391607594978096,
          "price_usd": 75.99,
          "value_jpy_fixed": 17544.12391713578
        },
        {
          "symbol": "ETH/USD",
          "quantity": 0.0610756318184149,
          "price_usd": 1886.8,
          "value_jpy_fixed": 17285.625317247785
        }
      ]
    },
    {
      "name": "07_pair_trade",
      "display_name": "#07",
      "status": "active",
      "total_jpy_fixed": 43502.71865281639,
      "pnl_jpy": -6497.2813471836125,
      "pnl_pct": -12.994562694367225,
      "trade_count_today": 0,
      "positions": []
    },
    {
      "name": "08_regime",
      "display_name": "#08",
      "status": "stopped",
      "total_jpy_fixed": 38853.43447583547,
      "pnl_jpy": -11146.565524164529,
      "pnl_pct": -22.293131048329055,
      "trade_count_today": 0,
      "positions": [
        {
          "symbol": "BTC/USD",
          "quantity": 0.0011177759698988267,
          "price_usd": 64680.2,
          "value_jpy_fixed": 10844.695993237514
        }
      ]
    },
    {
      "name": "09_ml_gate",
      "display_name": "#09",
      "status": "active",
      "total_jpy_fixed": 47796.59927235783,
      "pnl_jpy": -2203.400727642169,
      "pnl_pct": -4.406801455284338,
      "trade_count_today": 0,
      "positions": [
        {
          "symbol": "BTC/USD",
          "quantity": 0.0005342376979242056,
          "price_usd": 64680.2,
          "value_jpy_fixed": 5183.190172391581
        }
      ]
    },
    {
      "name": "10_deriv",
      "display_name": "#10",
      "status": "active",
      "total_jpy_fixed": 46325.289130774996,
      "pnl_jpy": -3674.710869225004,
      "pnl_pct": -7.349421738450008,
      "trade_count_today": 2,
      "positions": [
        {
          "symbol": "BTC/USD",
          "quantity": 0.0008495823539220568,
          "price_usd": 64680.2,
          "value_jpy_fixed": 8242.673485222413
        },
        {
          "symbol": "ETH/USD",
          "quantity": 0.03228684102458733,
          "price_usd": 1886.8,
          "value_jpy_fixed": 9137.821746778705
        }
      ]
    }
  ],
  "recent_trades": [
    {
      "timestamp": "2026-07-23T16:13:55.004842+00:00",
      "bot": "03",
      "action": "BUY",
      "symbol": "ETH/USD",
      "price": 283189.5,
      "quantity": 0.02937377693331027,
      "icon": "🟢"
    },
    {
      "timestamp": "2026-07-23T14:40:37.616041+00:00",
      "bot": "04",
      "action": "BUY",
      "symbol": "ETH/USD",
      "price": 285586.5,
      "quantity": 0.0656107719300259,
      "icon": "🟢"
    },
    {
      "timestamp": "2026-07-23T14:40:37.611577+00:00",
      "bot": "04",
      "action": "BUY",
      "symbol": "BTC/USD",
      "price": 9767730.0,
      "quantity": 0.0019292592768589583,
      "icon": "🟢"
    },
    {
      "timestamp": "2026-07-23T10:52:42.352412+00:00",
      "bot": "10",
      "action": "SELL",
      "symbol": "ETH/USD",
      "price": 289138.5,
      "quantity": 0.04848166168723737,
      "icon": "🔴"
    },
    {
      "timestamp": "2026-07-23T06:18:53.105335+00:00",
      "bot": "10",
      "action": "BUY",
      "symbol": "ETH/USD",
      "price": 288390.0,
      "quantity": 0.048593856067200916,
      "icon": "🟢"
    }
  ]
}