{
  "metadata": {
    "updated_at": "2026-04-25T11:50:49.856895+00:00",
    "usd_jpy_real": 159.946,
    "usd_jpy_fixed": 150.0
  },
  "summary": {
    "total_asset_fixed": 522995.1983597252,
    "total_asset_real": 538629.4970748549,
    "total_pnl": 22995.198359725182,
    "total_pnl_pct": 4.599039671945036,
    "active_bots": 10,
    "total_bots": 10
  },
  "bots": [
    {
      "name": "01_donchian",
      "display_name": "#01",
      "status": "active",
      "total_jpy_fixed": 53328.75838796831,
      "pnl_jpy": 3328.758387968308,
      "pnl_pct": 6.657516775936616,
      "trade_count_today": 7,
      "positions": [
        {
          "symbol": "BTC/USD",
          "quantity": 0.0018322353824401943,
          "price_usd": 77679.7,
          "value_jpy_fixed": 21349.124225600932
        },
        {
          "symbol": "ETH/USD",
          "quantity": 0.015348694281641984,
          "price_usd": 2314.02,
          "value_jpy_fixed": 5327.577831240777
        }
      ]
    },
    {
      "name": "02_ema_adx",
      "display_name": "#02",
      "status": "active",
      "total_jpy_fixed": 55271.563026908596,
      "pnl_jpy": 5271.563026908596,
      "pnl_pct": 10.543126053817192,
      "trade_count_today": 10,
      "positions": [
        {
          "symbol": "BTC/USD",
          "quantity": 0.0014254671261075729,
          "price_usd": 77679.7,
          "value_jpy_fixed": 16609.478807384763
        },
        {
          "symbol": "ETH/USD",
          "quantity": 0.04774524134737719,
          "price_usd": 2314.02,
          "value_jpy_fixed": 16572.516507398665
        }
      ]
    },
    {
      "name": "03_bb_zscore",
      "display_name": "#03",
      "status": "active",
      "total_jpy_fixed": 52773.87755847082,
      "pnl_jpy": 2773.87755847082,
      "pnl_pct": 5.547755116941641,
      "trade_count_today": 5,
      "positions": [
        {
          "symbol": "ETH/USD",
          "quantity": 0.030316601668369192,
          "price_usd": 2314.02,
          "value_jpy_fixed": 10522.983388895951
        }
      ]
    },
    {
      "name": "04_vwap",
      "display_name": "#04",
      "status": "active",
      "total_jpy_fixed": 52924.315041909475,
      "pnl_jpy": 2924.3150419094745,
      "pnl_pct": 5.848630083818949,
      "trade_count_today": 0,
      "positions": [
        {
          "symbol": "BTC/USD",
          "quantity": 0.000991167606343116,
          "price_usd": 77679.7,
          "value_jpy_fixed": 11549.0403465677
        },
        {
          "symbol": "ETH/USD",
          "quantity": 0.03020716405153067,
          "price_usd": 2314.02,
          "value_jpy_fixed": 10484.99726377845
        }
      ]
    },
    {
      "name": "05_squeeze",
      "display_name": "#05",
      "status": "active",
      "total_jpy_fixed": 55204.923200975674,
      "pnl_jpy": 5204.923200975674,
      "pnl_pct": 10.409846401951349,
      "trade_count_today": 16,
      "positions": [
        {
          "symbol": "BTC/USD",
          "quantity": 0.0014225836769708098,
          "price_usd": 77679.7,
          "value_jpy_fixed": 16575.88098779841
        }
      ]
    },
    {
      "name": "06_vol_momentum",
      "display_name": "#06",
      "status": "active",
      "total_jpy_fixed": 52171.290934493394,
      "pnl_jpy": 2171.290934493394,
      "pnl_pct": 4.342581868986788,
      "trade_count_today": 14,
      "positions": [
        {
          "symbol": "BTC/USD",
          "quantity": 0.0022366494176810203,
          "price_usd": 77679.7,
          "value_jpy_fixed": 26061.338365595453
        }
      ]
    },
    {
      "name": "07_pair_trade",
      "display_name": "#07",
      "status": "active",
      "total_jpy_fixed": 48994.686352283316,
      "pnl_jpy": -1005.3136477166845,
      "pnl_pct": -2.010627295433369,
      "trade_count_today": 1,
      "positions": [
        {
          "symbol": "ETH/USD",
          "quantity": 0.09869539688104478,
          "price_usd": 2314.02,
          "value_jpy_fixed": 34257.468343601286
        }
      ]
    },
    {
      "name": "08_regime",
      "display_name": "#08",
      "status": "active",
      "total_jpy_fixed": 53196.55362797527,
      "pnl_jpy": 3196.5536279752705,
      "pnl_pct": 6.39310725595054,
      "trade_count_today": 7,
      "positions": [
        {
          "symbol": "BTC/USD",
          "quantity": 0.0031935016270856604,
          "price_usd": 77679.7,
          "value_jpy_fixed": 37210.537251228896
        }
      ]
    },
    {
      "name": "09_ml_gate",
      "display_name": "#09",
      "status": "active",
      "total_jpy_fixed": 49706.0121220984,
      "pnl_jpy": -293.98787790159986,
      "pnl_pct": -0.5879757558031997,
      "trade_count_today": 0,
      "positions": [
        {
          "symbol": "BTC/USD",
          "quantity": 0.00042086040221690085,
          "price_usd": 77679.7,
          "value_jpy_fixed": 4903.846467913229
        },
        {
          "symbol": "ETH/USD",
          "quantity": 0.01423992908821011,
          "price_usd": 2314.02,
          "value_jpy_fixed": 4942.722106304993
        }
      ]
    },
    {
      "name": "10_deriv",
      "display_name": "#10",
      "status": "active",
      "total_jpy_fixed": 49423.21810664183,
      "pnl_jpy": -576.781893358173,
      "pnl_pct": -1.153563786716346,
      "trade_count_today": 0,
      "positions": [
        {
          "symbol": "BTC/USD",
          "quantity": 0.0008417208044338017,
          "price_usd": 77679.7,
          "value_jpy_fixed": 9807.692935826459
        },
        {
          "symbol": "ETH/USD",
          "quantity": 0.02769359430507795,
          "price_usd": 2314.02,
          "value_jpy_fixed": 9612.529664075473
        }
      ]
    }
  ],
  "recent_trades": [
    {
      "timestamp": "2026-04-25T11:04:06.316997+00:00",
      "bot": "08",
      "action": "BUY",
      "symbol": "BTC/USD",
      "price": 11670225.0,
      "quantity": 0.0018178657291871348,
      "icon": "🟢"
    },
    {
      "timestamp": "2026-04-25T11:04:06.263820+00:00",
      "bot": "06",
      "action": "SELL",
      "symbol": "ETH/USD",
      "price": 347902.5,
      "quantity": 0.03006451431931796,
      "icon": "🔴"
    },
    {
      "timestamp": "2026-04-25T11:04:06.259936+00:00",
      "bot": "06",
      "action": "BUY",
      "symbol": "BTC/USD",
      "price": 11670225.0,
      "quantity": 0.0013390143423926049,
      "icon": "🟢"
    },
    {
      "timestamp": "2026-04-25T11:04:06.249863+00:00",
      "bot": "05",
      "action": "SELL",
      "symbol": "SOL/USD",
      "price": 12984.0,
      "quantity": 0.42532270436454644,
      "icon": "🔴"
    },
    {
      "timestamp": "2026-04-25T11:04:06.221408+00:00",
      "bot": "02",
      "action": "SELL",
      "symbol": "ETH/USD",
      "price": 347902.5,
      "quantity": 0.06358894184400801,
      "icon": "🔴"
    },
    {
      "timestamp": "2026-04-25T11:04:06.208841+00:00",
      "bot": "01",
      "action": "SELL",
      "symbol": "ETH/USD",
      "price": 347902.5,
      "quantity": 0.04596405354146062,
      "icon": "🔴"
    },
    {
      "timestamp": "2026-04-25T10:05:18.784350+00:00",
      "bot": "08",
      "action": "SELL",
      "symbol": "ETH/USD",
      "price": 347892.00000000006,
      "quantity": 0.10718462574591653,
      "icon": "🔴"
    },
    {
      "timestamp": "2026-04-25T10:05:18.735737+00:00",
      "bot": "07",
      "action": "BUY",
      "symbol": "ETH/USD",
      "price": 347892.00000000006,
      "quantity": 0.09869539688104478,
      "icon": "🟢"
    },
    {
      "timestamp": "2026-04-25T10:05:18.729260+00:00",
      "bot": "06",
      "action": "SELL",
      "symbol": "SOL/USD",
      "price": 12991.5,
      "quantity": 1.2079932796364086,
      "icon": "🔴"
    },
    {
      "timestamp": "2026-04-25T10:05:18.725925+00:00",
      "bot": "06",
      "action": "SELL",
      "symbol": "ETH/USD",
      "price": 347892.00000000006,
      "quantity": 0.045041452011738245,
      "icon": "🔴"
    },
    {
      "timestamp": "2026-04-25T10:05:18.716404+00:00",
      "bot": "05",
      "action": "SELL",
      "symbol": "SOL/USD",
      "price": 12991.5,
      "quantity": 0.8502976692996889,
      "icon": "🔴"
    },
    {
      "timestamp": "2026-04-25T10:05:18.713084+00:00",
      "bot": "05",
      "action": "SELL",
      "symbol": "ETH/USD",
      "price": 347892.00000000006,
      "quantity": 0.047604417388019474,
      "icon": "🔴"
    },
    {
      "timestamp": "2026-04-25T10:05:18.696828+00:00",
      "bot": "03",
      "action": "BUY",
      "symbol": "ETH/USD",
      "price": 347892.00000000006,
      "quantity": 0.030316601668369192,
      "icon": "🟢"
    },
    {
      "timestamp": "2026-04-25T09:10:09.955810+00:00",
      "bot": "08",
      "action": "BUY",
      "symbol": "ETH/USD",
      "price": 347941.5,
      "quantity": 0.06114361858233195,
      "icon": "🟢"
    },
    {
      "timestamp": "2026-04-25T09:10:09.917703+00:00",
      "bot": "05",
      "action": "SELL",
      "symbol": "SOL/USD",
      "price": 12997.5,
      "quantity": 0.42753180875413177,
      "icon": "🔴"
    },
    {
      "timestamp": "2026-04-25T09:10:09.879079+00:00",
      "bot": "02",
      "action": "BUY",
      "symbol": "ETH/USD",
      "price": 347941.5,
      "quantity": 0.06358921849855097,
      "icon": "🟢"
    },
    {
      "timestamp": "2026-04-25T09:10:09.812311+00:00",
      "bot": "02",
      "action": "BUY",
      "symbol": "BTC/USD",
      "price": 11644995.0,
      "quantity": 0.0009487761799617574,
      "icon": "🟢"
    },
    {
      "timestamp": "2026-04-25T08:12:21.506343+00:00",
      "bot": "06",
      "action": "BUY",
      "symbol": "SOL/USD",
      "price": 12967.5,
      "quantity": 1.2079932796364086,
      "icon": "🟢"
    },
    {
      "timestamp": "2026-04-25T08:12:21.503705+00:00",
      "bot": "06",
      "action": "BUY",
      "symbol": "ETH/USD",
      "price": 347682.0,
      "quantity": 0.045024694253373417,
      "icon": "🟢"
    },
    {
      "timestamp": "2026-04-25T08:12:21.501182+00:00",
      "bot": "06",
      "action": "BUY",
      "symbol": "BTC/USD",
      "price": 11639835.0,
      "quantity": 0.0004485625758744208,
      "icon": "🟢"
    },
    {
      "timestamp": "2026-04-25T08:12:21.492915+00:00",
      "bot": "05",
      "action": "BUY",
      "symbol": "SOL/USD",
      "price": 12967.5,
      "quantity": 1.703152182418367,
      "icon": "🟢"
    },
    {
      "timestamp": "2026-04-25T08:12:21.489885+00:00",
      "bot": "05",
      "action": "BUY",
      "symbol": "ETH/USD",
      "price": 347682.0,
      "quantity": 0.047604417388019474,
      "icon": "🟢"
    },
    {
      "timestamp": "2026-04-25T08:12:21.487193+00:00",
      "bot": "05",
      "action": "BUY",
      "symbol": "BTC/USD",
      "price": 11639835.0,
      "quantity": 0.0014225836769708098,
      "icon": "🟢"
    },
    {
      "timestamp": "2026-04-25T08:12:21.473906+00:00",
      "bot": "03",
      "action": "SELL",
      "symbol": "ETH/USD",
      "price": 347682.0,
      "quantity": 0.030383589045253147,
      "icon": "🔴"
    },
    {
      "timestamp": "2026-04-25T08:12:21.471284+00:00",
      "bot": "03",
      "action": "SELL",
      "symbol": "BTC/USD",
      "price": 11639835.0,
      "quantity": 0.0009074623489245927,
      "icon": "🔴"
    },
    {
      "timestamp": "2026-04-25T08:12:21.457898+00:00",
      "bot": "02",
      "action": "BUY",
      "symbol": "ETH/USD",
      "price": 347682.0,
      "quantity": 0.03180415704101607,
      "icon": "🟢"
    },
    {
      "timestamp": "2026-04-25T08:12:21.446954+00:00",
      "bot": "01",
      "action": "BUY",
      "symbol": "ETH/USD",
      "price": 347682.0,
      "quantity": 0.04594627330878304,
      "icon": "🟢"
    },
    {
      "timestamp": "2026-04-25T08:12:21.443551+00:00",
      "bot": "01",
      "action": "BUY",
      "symbol": "BTC/USD",
      "price": 11639835.0,
      "quantity": 0.0013729952320359604,
      "icon": "🟢"
    },
    {
      "timestamp": "2026-04-25T07:11:47.552574+00:00",
      "bot": "06",
      "action": "BUY",
      "symbol": "ETH/USD",
      "price": 347254.50000000006,
      "quantity": 0.01502211108215642,
      "icon": "🟢"
    },
    {
      "timestamp": "2026-04-25T07:11:47.549796+00:00",
      "bot": "06",
      "action": "BUY",
      "symbol": "BTC/USD",
      "price": 11623500.0,
      "quantity": 0.00044907249941399466,
      "icon": "🟢"
    },
    {
      "timestamp": "2026-04-25T07:11:47.541350+00:00",
      "bot": "05",
      "action": "SELL",
      "symbol": "ETH/USD",
      "price": 347254.50000000006,
      "quantity": 0.047744490522615604,
      "icon": "🔴"
    },
    {
      "timestamp": "2026-04-25T07:11:47.527583+00:00",
      "bot": "03",
      "action": "BUY",
      "symbol": "ETH/USD",
      "price": 347254.50000000006,
      "quantity": 0.030383589045253147,
      "icon": "🟢"
    },
    {
      "timestamp": "2026-04-25T05:58:57.102497+00:00",
      "bot": "08",
      "action": "SELL",
      "symbol": "BTC/USD",
      "price": 11631915.0,
      "quantity": 0.0018326443262573844,
      "icon": "🔴"
    },
    {
      "timestamp": "2026-04-25T05:58:57.047932+00:00",
      "bot": "06",
      "action": "SELL",
      "symbol": "SOL/USD",
      "price": 12933.0,
      "quantity": 0.807414445824106,
      "icon": "🔴"
    },
    {
      "timestamp": "2026-04-25T05:58:57.044885+00:00",
      "bot": "06",
      "action": "SELL",
      "symbol": "ETH/USD",
      "price": 347473.49999999994,
      "quantity": 0.060231944116195674,
      "icon": "🔴"
    },
    {
      "timestamp": "2026-04-25T05:58:57.041219+00:00",
      "bot": "06",
      "action": "SELL",
      "symbol": "BTC/USD",
      "price": 11631915.0,
      "quantity": 0.0009003520870181408,
      "icon": "🔴"
    },
    {
      "timestamp": "2026-04-25T05:58:57.030520+00:00",
      "bot": "05",
      "action": "SELL",
      "symbol": "SOL/USD",
      "price": 12933.0,
      "quantity": 1.2836065180739535,
      "icon": "🔴"
    },
    {
      "timestamp": "2026-04-25T05:58:57.024532+00:00",
      "bot": "05",
      "action": "BUY",
      "symbol": "ETH/USD",
      "price": 347473.49999999994,
      "quantity": 0.031794094303565695,
      "icon": "🟢"
    },
    {
      "timestamp": "2026-04-25T05:58:57.020709+00:00",
      "bot": "05",
      "action": "SELL",
      "symbol": "BTC/USD",
      "price": 11631915.0,
      "quantity": 0.0014278784972188412,
      "icon": "🔴"
    },
    {
      "timestamp": "2026-04-25T05:58:57.003151+00:00",
      "bot": "03",
      "action": "BUY",
      "symbol": "BTC/USD",
      "price": 11631915.0,
      "quantity": 0.0009074623489245927,
      "icon": "🟢"
    },
    {
      "timestamp": "2026-04-25T05:58:56.986680+00:00",
      "bot": "02",
      "action": "SELL",
      "symbol": "ETH/USD",
      "price": 347473.49999999994,
      "quantity": 0.01600751515203044,
      "icon": "🔴"
    },
    {
      "timestamp": "2026-04-25T05:58:56.982852+00:00",
      "bot": "02",
      "action": "SELL",
      "symbol": "BTC/USD",
      "price": 11631915.0,
      "quantity": 0.0033358446616706043,
      "icon": "🔴"
    },
    {
      "timestamp": "2026-04-25T05:58:56.969492+00:00",
      "bot": "01",
      "action": "SELL",
      "symbol": "ETH/USD",
      "price": 347473.49999999994,
      "quantity": 0.046130499524230026,
      "icon": "🔴"
    },
    {
      "timestamp": "2026-04-25T05:58:56.965544+00:00",
      "bot": "01",
      "action": "SELL",
      "symbol": "BTC/USD",
      "price": 11631915.0,
      "quantity": 0.0013753607712603593,
      "icon": "🔴"
    },
    {
      "timestamp": "2026-04-25T04:09:00.030317+00:00",
      "bot": "08",
      "action": "BUY",
      "symbol": "BTC/USD",
      "price": 11650260.0,
      "quantity": 0.0018308671209763454,
      "icon": "🟢"
    },
    {
      "timestamp": "2026-04-25T04:08:59.991133+00:00",
      "bot": "06",
      "action": "BUY",
      "symbol": "SOL/USD",
      "price": 12966.0,
      "quantity": 0.8059004931999658,
      "icon": "🟢"
    },
    {
      "timestamp": "2026-04-25T04:08:59.849246+00:00",
      "bot": "06",
      "action": "SELL",
      "symbol": "BTC/USD",
      "price": 11650260.0,
      "quantity": 0.0013522565322890473,
      "icon": "🔴"
    },
    {
      "timestamp": "2026-04-25T04:08:59.800824+00:00",
      "bot": "05",
      "action": "SELL",
      "symbol": "ETH/USD",
      "price": 347764.5,
      "quantity": 0.03192151451791493,
      "icon": "🔴"
    },
    {
      "timestamp": "2026-04-25T04:08:59.743311+00:00",
      "bot": "05",
      "action": "BUY",
      "symbol": "BTC/USD",
      "price": 11650260.0,
      "quantity": 0.00047323339937451717,
      "icon": "🟢"
    },
    {
      "timestamp": "2026-04-25T04:08:59.559125+00:00",
      "bot": "02",
      "action": "BUY",
      "symbol": "ETH/USD",
      "price": 347764.5,
      "quantity": 0.015978088326466765,
      "icon": "🟢"
    }
  ]
}