{
  "metadata": {
    "updated_at": "2026-06-14T20:39:28.345100+00:00",
    "usd_jpy_real": 162.84,
    "usd_jpy_fixed": 150.0
  },
  "summary": {
    "total_asset_fixed": 411095.31943980994,
    "total_asset_real": 421659.6124236012,
    "total_pnl": -88904.68056019006,
    "total_pnl_pct": -17.780936112038013,
    "active_bots": 5,
    "total_bots": 10
  },
  "bots": [
    {
      "name": "01_donchian",
      "display_name": "#01",
      "status": "stopped",
      "total_jpy_fixed": 39043.76642453595,
      "pnl_jpy": -10956.233575464052,
      "pnl_pct": -21.9124671509281,
      "trade_count_today": 0,
      "positions": [
        {
          "symbol": "ETH/USD",
          "quantity": 0.0600260064610979,
          "price_usd": 1669.86,
          "value_jpy_fixed": 15035.25407236934
        },
        {
          "symbol": "BTC/USD",
          "quantity": 0.0004193929525974449,
          "price_usd": 63989.8,
          "value_jpy_fixed": 4025.5306737179976
        }
      ]
    },
    {
      "name": "02_ema_adx",
      "display_name": "#02",
      "status": "stopped",
      "total_jpy_fixed": 39618.27963579337,
      "pnl_jpy": -10381.72036420663,
      "pnl_pct": -20.76344072841326,
      "trade_count_today": 0,
      "positions": [
        {
          "symbol": "ETH/USD",
          "quantity": 0.014442908385121273,
          "price_usd": 1669.86,
          "value_jpy_fixed": 3617.645249396791
        }
      ]
    },
    {
      "name": "03_bb_zscore",
      "display_name": "#03",
      "status": "active",
      "total_jpy_fixed": 42757.37453001159,
      "pnl_jpy": -7242.625469988408,
      "pnl_pct": -14.485250939976819,
      "trade_count_today": 12,
      "positions": []
    },
    {
      "name": "04_vwap",
      "display_name": "#04",
      "status": "active",
      "total_jpy_fixed": 47026.46540844094,
      "pnl_jpy": -2973.5345915590588,
      "pnl_pct": -5.947069183118117,
      "trade_count_today": 0,
      "positions": [
        {
          "symbol": "BTC/USD",
          "quantity": 0.001004854975642115,
          "price_usd": 63989.8,
          "value_jpy_fixed": 9645.070338051573
        },
        {
          "symbol": "ETH/USD",
          "quantity": 0.037317789692077497,
          "price_usd": 1669.86,
          "value_jpy_fixed": 9347.32264428188
        }
      ]
    },
    {
      "name": "05_squeeze",
      "display_name": "#05",
      "status": "stopped",
      "total_jpy_fixed": 36795.5372053155,
      "pnl_jpy": -13204.4627946845,
      "pnl_pct": -26.408925589368998,
      "trade_count_today": 0,
      "positions": [
        {
          "symbol": "SOL/USD",
          "quantity": 0.9323998058153873,
          "price_usd": 67.85,
          "value_jpy_fixed": 9489.499023686103
        },
        {
          "symbol": "BTC/USD",
          "quantity": 0.0003445061114368947,
          "price_usd": 63989.8,
          "value_jpy_fixed": 3306.731575443691
        }
      ]
    },
    {
      "name": "06_vol_momentum",
      "display_name": "#06",
      "status": "stopped",
      "total_jpy_fixed": 30962.971812033702,
      "pnl_jpy": -19037.028187966298,
      "pnl_pct": -38.0740563759326,
      "trade_count_today": 0,
      "positions": [
        {
          "symbol": "SOL/USD",
          "quantity": 1.5391607594978096,
          "price_usd": 67.85,
          "value_jpy_fixed": 15664.808629788957
        },
        {
          "symbol": "ETH/USD",
          "quantity": 0.0610756318184149,
          "price_usd": 1669.86,
          "value_jpy_fixed": 15298.163182244745
        }
      ]
    },
    {
      "name": "07_pair_trade",
      "display_name": "#07",
      "status": "active",
      "total_jpy_fixed": 43721.61125348414,
      "pnl_jpy": -6278.388746515862,
      "pnl_pct": -12.556777493031724,
      "trade_count_today": 2,
      "positions": []
    },
    {
      "name": "08_regime",
      "display_name": "#08",
      "status": "stopped",
      "total_jpy_fixed": 38737.67759639275,
      "pnl_jpy": -11262.32240360725,
      "pnl_pct": -22.5246448072145,
      "trade_count_today": 0,
      "positions": [
        {
          "symbol": "BTC/USD",
          "quantity": 0.0011177759698988267,
          "price_usd": 63989.8,
          "value_jpy_fixed": 10728.939113794793
        }
      ]
    },
    {
      "name": "09_ml_gate",
      "display_name": "#09",
      "status": "active",
      "total_jpy_fixed": 47301.79985836793,
      "pnl_jpy": -2698.200141632071,
      "pnl_pct": -5.396400283264142,
      "trade_count_today": 0,
      "positions": [
        {
          "symbol": "BTC/USD",
          "quantity": 0.0004989086629285492,
          "price_usd": 63989.8,
          "value_jpy_fixed": 4788.759833859792
        },
        {
          "symbol": "ETH/USD",
          "quantity": 0.0187764171503801,
          "price_usd": 1669.86,
          "value_jpy_fixed": 4703.098191410057
        }
      ]
    },
    {
      "name": "10_deriv",
      "display_name": "#10",
      "status": "active",
      "total_jpy_fixed": 45129.83571543405,
      "pnl_jpy": -4870.164284565952,
      "pnl_pct": -9.740328569131904,
      "trade_count_today": 0,
      "positions": [
        {
          "symbol": "BTC/USD",
          "quantity": 0.0008495823539220568,
          "price_usd": 63989.8,
          "value_jpy_fixed": 8154.6907366502455
        },
        {
          "symbol": "ETH/USD",
          "quantity": 0.03836299408899608,
          "price_usd": 1669.86,
          "value_jpy_fixed": 9609.124396417648
        }
      ]
    }
  ],
  "recent_trades": [
    {
      "timestamp": "2026-06-14T20:18:19.052172+00:00",
      "bot": "03",
      "action": "SELL",
      "symbol": "ETH/USD",
      "price": 249503.99999999997,
      "quantity": 0.03426405446528408,
      "icon": "🔴"
    },
    {
      "timestamp": "2026-06-14T19:00:12.598039+00:00",
      "bot": "07",
      "action": "SELL",
      "symbol": "BTC/USD",
      "price": 9566340.0,
      "quantity": 0.0032005008716650338,
      "icon": "🔴"
    },
    {
      "timestamp": "2026-06-14T19:00:12.572967+00:00",
      "bot": "03",
      "action": "SELL",
      "symbol": "BTC/USD",
      "price": 9566340.0,
      "quantity": 0.0008931072878908426,
      "icon": "🔴"
    },
    {
      "timestamp": "2026-06-14T17:47:20.618677+00:00",
      "bot": "07",
      "action": "BUY",
      "symbol": "BTC/USD",
      "price": 9573015.0,
      "quantity": 0.0032005008716650338,
      "icon": "🟢"
    },
    {
      "timestamp": "2026-06-14T17:47:20.591426+00:00",
      "bot": "03",
      "action": "BUY",
      "symbol": "ETH/USD",
      "price": 249450.0,
      "quantity": 0.03426405446528408,
      "icon": "🟢"
    },
    {
      "timestamp": "2026-06-14T17:47:20.588530+00:00",
      "bot": "03",
      "action": "BUY",
      "symbol": "BTC/USD",
      "price": 9573015.0,
      "quantity": 0.0008931072878908426,
      "icon": "🟢"
    },
    {
      "timestamp": "2026-06-14T16:11:38.226769+00:00",
      "bot": "03",
      "action": "SELL",
      "symbol": "BTC/USD",
      "price": 9607500.0,
      "quantity": 0.003555819819430035,
      "icon": "🔴"
    },
    {
      "timestamp": "2026-06-14T14:39:40.938878+00:00",
      "bot": "03",
      "action": "SELL",
      "symbol": "ETH/USD",
      "price": 248404.5,
      "quantity": 0.03423287402240416,
      "icon": "🔴"
    },
    {
      "timestamp": "2026-06-14T14:39:40.935864+00:00",
      "bot": "03",
      "action": "BUY",
      "symbol": "BTC/USD",
      "price": 9585930.0,
      "quantity": 0.0026672627214002747,
      "icon": "🟢"
    },
    {
      "timestamp": "2026-06-14T12:22:16.313050+00:00",
      "bot": "03",
      "action": "BUY",
      "symbol": "ETH/USD",
      "price": 250911.0,
      "quantity": 0.03423287402240416,
      "icon": "🟢"
    },
    {
      "timestamp": "2026-06-14T12:22:16.309880+00:00",
      "bot": "03",
      "action": "BUY",
      "symbol": "BTC/USD",
      "price": 9669585.0,
      "quantity": 0.0008885570980297605,
      "icon": "🟢"
    },
    {
      "timestamp": "2026-06-14T10:22:58.331330+00:00",
      "bot": "03",
      "action": "SELL",
      "symbol": "ETH/USD",
      "price": 251575.5,
      "quantity": 0.03419698596160201,
      "icon": "🔴"
    },
    {
      "timestamp": "2026-06-14T06:50:43.379997+00:00",
      "bot": "03",
      "action": "BUY",
      "symbol": "ETH/USD",
      "price": 251356.5,
      "quantity": 0.03419698596160201,
      "icon": "🟢"
    },
    {
      "timestamp": "2026-06-14T02:03:37.111416+00:00",
      "bot": "03",
      "action": "SELL",
      "symbol": "ETH/USD",
      "price": 252448.5,
      "quantity": 0.03413002335676834,
      "icon": "🔴"
    },
    {
      "timestamp": "2026-06-13T23:48:13.334772+00:00",
      "bot": "09",
      "action": "BUY",
      "symbol": "ETH/USD",
      "price": 251889.0,
      "quantity": 0.0187764171503801,
      "icon": "🟢"
    },
    {
      "timestamp": "2026-06-13T23:48:13.227293+00:00",
      "bot": "03",
      "action": "BUY",
      "symbol": "ETH/USD",
      "price": 251889.0,
      "quantity": 0.03413002335676834,
      "icon": "🟢"
    },
    {
      "timestamp": "2026-06-13T22:46:03.330409+00:00",
      "bot": "09",
      "action": "SELL",
      "symbol": "ETH/USD",
      "price": 252444.0,
      "quantity": 0.018677829636971274,
      "icon": "🔴"
    },
    {
      "timestamp": "2026-06-13T21:37:55.096931+00:00",
      "bot": "03",
      "action": "SELL",
      "symbol": "ETH/USD",
      "price": 251778.0,
      "quantity": 0.03419668748207652,
      "icon": "🔴"
    }
  ]
}